openProduction/__init__.py
openProduction/log.py
openProduction/main.py
openProduction/UI/__init__.py
openProduction/UI/mainUI.py
openProduction/UI/qml/Installation.qml
openProduction/UI/qml/MainScreen.pro
openProduction/UI/qml/MenuAnim.qml
openProduction/UI/qml/ProductEquip.qml
openProduction/UI/qml/SideMenuModel.qml
openProduction/UI/qml/TitleBar.qml
openProduction/UI/qml/main.qml
openProduction/UI/qml/qml.qrc
openProduction/UI/qml/Common/BusyIndication.qml
openProduction/UI/qml/Common/BusyIndicationPopup.qml
openProduction/UI/qml/Common/BusyIndicationWindow.qml
openProduction/UI/qml/Common/ErrorIcon.qml
openProduction/UI/qml/Common/MultilineText.qml
openProduction/UI/qml/Common/ParamsViewer.qml
openProduction/UI/qml/Common/SuccessIcon.qml
openProduction/UI/qml/Dashboard/Dashboard.qml
openProduction/UI/qml/ProductChoose/ProductChoose.qml
openProduction/UI/qml/ProductRun/ProductEquip.qml
openProduction/UI/qml/ProductRun/ProductRun.qml
openProduction/UI/qml/TestRunnerSimple/BusyIndication.qml
openProduction/UI/qml/TestRunnerSimple/ErrorIcon.qml
openProduction/UI/qml/TestRunnerSimple/MultilineText.qml
openProduction/UI/qml/TestRunnerSimple/SuccessIcon.qml
openProduction/UI/qml/TestRunnerSimple/TestRunnerSimple.qml
openProduction/UI/qml/icons/bookmark.png
openProduction/UI/qml/icons/change.png
openProduction/UI/qml/icons/change_white.png
openProduction/UI/qml/icons/create.png
openProduction/UI/qml/icons/create_white.png
openProduction/UI/qml/icons/dashboard.png
openProduction/UI/qml/icons/dashboard_white.png
openProduction/UI/qml/icons/details.png
openProduction/UI/qml/icons/documentation.png
openProduction/UI/qml/icons/drawerWhite.png
openProduction/UI/qml/icons/export.png
openProduction/UI/qml/icons/export_white.png
openProduction/UI/qml/icons/file.png
openProduction/UI/qml/icons/full-box.png
openProduction/UI/qml/icons/git.png
openProduction/UI/qml/icons/iconsSource.txt
openProduction/UI/qml/icons/img2.png
openProduction/UI/qml/icons/import.png
openProduction-0.0.33.dist-info/LICENSE
openProduction-0.0.33.dist-info/METADATA
openProduction-0.0.33.dist-info/WHEEL
openProduction-0.0.33.dist-info/top_level.txt
openProduction-0.0.33.dist-info/RECORD
